{
	"required": true,
	"package": "com.faboslav.structurify.common.mixin",
	"refmap": "${modId}.refmap.json",
	"compatibilityLevel": "JAVA_${javaVersion}",
	"minVersion": "0.8",
	"plugin": "com.faboslav.structurify.common.mixin.plugin.StructurifyMixinPlugin",
	"injectors": {
		"defaultRequire": 1
	},
	"mixins": [
		"ChunkGeneratorMixin",
		"LevelChunkMixin",
		"LocateCommandInvoker",
		"LocateCommandMixin",
		"ResourceKeyArgumentInvoker",
		"ResourcePackManagerAccessor",
		"StructureManagerMixin",
		"level.BiasedToBottomHeightAccessor",
		"level.TrapezoidHeightAccessor",
		"level.UniformHeightAccessor",
		"level.VeryBiasedToBottomHeightAccessor",
		"structure.StructureMixin",
		"structure.StructureSelectionEntryMixin",
		"structure.StructureSetMixin",
		"structure.StructureTemplatePoolMixin",
		"structure.jigsaw.JigsawStructureAccessor",
		"structure.jigsaw.JigsawStructureMixin",
		"structure.jigsaw.compat.RepurposedStructuresGenericJigsawStructureMixin",
		"structure.jigsaw.compat.YungJigsawStructureMixin",
		"structure.placement.RandomSpreadStructurePlacementMixin",
		"structure.placement.StructurePlacementMixin",
		"structure.placement.compat.RepurposedStructuresModifySpreadMixin",
		"structure.pools.SinglePoolElementAccessor",
		"yacl.ControllerWidgetMixin"
	],
	"client": [
		"AbstractWidgetInvoker",
		"WorldOpenFlowsMixin",
		"yacl.CategoryTabAccessor",
		"yacl.ElementListWidgetExtMixin",
		"yacl.GroupSeparatorEntryAccessor",
		"yacl.LabelControllerElementMixin",
		"yacl.OptionImplMixin",
		"yacl.OptionListWidgetMixin",
		"yacl.YACLScreenMixin"
	]
}
